hypergumbo_lang_mainstream/__init__.py
hypergumbo_lang_mainstream/bash.py
hypergumbo_lang_mainstream/c.py
hypergumbo_lang_mainstream/cmake.py
hypergumbo_lang_mainstream/cpp.py
hypergumbo_lang_mainstream/csharp.py
hypergumbo_lang_mainstream/css.py
hypergumbo_lang_mainstream/dockerfile.py
hypergumbo_lang_mainstream/gitignore.py
hypergumbo_lang_mainstream/go.py
hypergumbo_lang_mainstream/groovy.py
hypergumbo_lang_mainstream/html.py
hypergumbo_lang_mainstream/ini.py
hypergumbo_lang_mainstream/java.py
hypergumbo_lang_mainstream/js_ts.py
hypergumbo_lang_mainstream/json_config.py
hypergumbo_lang_mainstream/kotlin.py
hypergumbo_lang_mainstream/lua.py
hypergumbo_lang_mainstream/make.py
hypergumbo_lang_mainstream/markdown.py
hypergumbo_lang_mainstream/objc.py
hypergumbo_lang_mainstream/perl.py
hypergumbo_lang_mainstream/php.py
hypergumbo_lang_mainstream/powershell.py
hypergumbo_lang_mainstream/properties.py
hypergumbo_lang_mainstream/py.py
hypergumbo_lang_mainstream/requirements.py
hypergumbo_lang_mainstream/ruby.py
hypergumbo_lang_mainstream/rust.py
hypergumbo_lang_mainstream/scala.py
hypergumbo_lang_mainstream/sql.py
hypergumbo_lang_mainstream/swift.py
hypergumbo_lang_mainstream/toml_config.py
hypergumbo_lang_mainstream/xml_config.py
hypergumbo_lang_mainstream/yaml_ansible.py
hypergumbo_lang_mainstream-2.0.0.dist-info/METADATA
hypergumbo_lang_mainstream-2.0.0.dist-info/WHEEL
hypergumbo_lang_mainstream-2.0.0.dist-info/entry_points.txt
hypergumbo_lang_mainstream-2.0.0.dist-info/RECORD
